setup.py
gardenbox/Alerts.py
gardenbox/__init__.py
gardenbox.egg-info/PKG-INFO
gardenbox.egg-info/SOURCES.txt
gardenbox.egg-info/dependency_links.txt
gardenbox.egg-info/not-zip-safe
gardenbox.egg-info/top_level.txt