Metadata-Version: 1.0
Name: gardenbox
Version: 0.3
Summary: Shared package for GardenBox usage
Home-page: https://gitlab.imerir.com/anatoli/garden-box
Author: Imerir
Author-email: anthony.natoli@imerir.com
License: MIT
Platform: UNKNOWN
